clichatapp/__init__.py
clichatapp/__main__.py
clichatapp/main.py
clichatapp-0.1.12.1.dist-info/entry_points.txt
clichatapp-0.1.12.1.dist-info/METADATA
clichatapp-0.1.12.1.dist-info/WHEEL
clichatapp-0.1.12.1.dist-info/RECORD
