Metadata-Version: 2.1
Name: clichatapp
Version: 0.1.12.1
Summary: 
Author: JoseMRodriguezM
Author-email: jmrodriguezm13@gmail.com
Requires-Python: >=3.11,<4.0
Classifier: Programming Language :: Python :: 3
Classifier: Programming Language :: Python :: 3.11
Classifier: Programming Language :: Python :: 3.12
Requires-Dist: langchain (>=0.1.16,<0.2.0)
Requires-Dist: langchain-openai (>=0.1.4,<0.2.0)
Requires-Dist: python-dotenv (>=1.0.1,<2.0.0)
Requires-Dist: rich (>=13.7.1,<14.0.0)
Requires-Dist: typer[all] (>=0.12.3,<0.13.0)
Requires-Dist: yaspin (>=3.0.2,<4.0.0)
